README.txt
setup.py
django_panorama.egg-info/PKG-INFO
django_panorama.egg-info/SOURCES.txt
django_panorama.egg-info/dependency_links.txt
django_panorama.egg-info/entry_points.txt
django_panorama.egg-info/not-zip-safe
django_panorama.egg-info/requires.txt
django_panorama.egg-info/top_level.txt
docs/HISTORY.txt
panorama/__init__.py
panorama/admin.py
panorama/models.py
panorama/settings.py
panorama/test_settings.py
panorama/test_urls.py
panorama/tests.py
panorama/urls.py
panorama/views.py
panorama/fixtures/panorama.json
panorama/locale/en/LC_MESSAGES/django.mo
panorama/locale/en/LC_MESSAGES/django.po
panorama/locale/es/LC_MESSAGES/django.mo
panorama/locale/es/LC_MESSAGES/django.po
panorama/locale/eu/LC_MESSAGES/django.mo
panorama/locale/eu/LC_MESSAGES/django.po
panorama/migrations/0001_initial.py
panorama/migrations/0002_auto__add_panorama_display_fields.py
panorama/migrations/0003_auto__add_panoramalink.py
panorama/migrations/0004_rename_models.py
panorama/migrations/__init__.py
panorama/static/panorama/admin.css
panorama/static/panorama/jquery.fancybox-1.3.4.css
panorama/static/panorama/jquery.panorama.css
panorama/static/panorama/imgs/blank.gif
panorama/static/panorama/imgs/fancy_close.png
panorama/static/panorama/imgs/fancy_loading.png
panorama/static/panorama/imgs/fancy_nav_left.png
panorama/static/panorama/imgs/fancy_nav_right.png
panorama/static/panorama/imgs/fancy_shadow_e.png
panorama/static/panorama/imgs/fancy_shadow_n.png
panorama/static/panorama/imgs/fancy_shadow_ne.png
panorama/static/panorama/imgs/fancy_shadow_nw.png
panorama/static/panorama/imgs/fancy_shadow_s.png
panorama/static/panorama/imgs/fancy_shadow_se.png
panorama/static/panorama/imgs/fancy_shadow_sw.png
panorama/static/panorama/imgs/fancy_shadow_w.png
panorama/static/panorama/imgs/fancy_title_left.png
panorama/static/panorama/imgs/fancy_title_main.png
panorama/static/panorama/imgs/fancy_title_over.png
panorama/static/panorama/imgs/fancy_title_right.png
panorama/static/panorama/imgs/fancybox-x.png
panorama/static/panorama/imgs/fancybox-y.png
panorama/static/panorama/imgs/fancybox.png
panorama/static/panorama/js/OpenLayers.js
panorama/static/panorama/js/jquery.advanced-panorama.js
panorama/static/panorama/js/jquery.fancybox-1.3.1.pack.js
