Metadata-Version: 1.0
Name: django-panorama
Version: 1.2
Summary: Show panoramic photos in django
Home-page: http://lagunak.gisa-elkartea.org/projects/djangopanorama
Author: Maider Likona
Author-email: pisoni@gisa-elkartea.org
License: GPL
Platform: UNKNOWN
Classifier: Programming Language :: Python
Classifier: Topic :: Software Development :: Libraries :: Python Modules
